{
  "id": "4510220",
  "name": "qg二轮",
  "font_family": "iconfont",
  "css_prefix_text": "icon-",
  "description": "",
  "glyphs": [
    {
      "icon_id": "1240",
      "name": "图片",
      "font_class": "tupian",
      "unicode": "e600",
      "unicode_decimal": 58880
    },
    {
      "icon_id": "321992",
      "name": "personal-center",
      "font_class": "gerenzhongxin",
      "unicode": "e70b",
      "unicode_decimal": 59147
    },
    {
      "icon_id": "398280",
      "name": "白天模式，明亮模式",
      "font_class": "baitianmoshimingliangmoshi",
      "unicode": "e632",
      "unicode_decimal": 58930
    },
    {
      "icon_id": "430545",
      "name": "上箭头",
      "font_class": "arrow-up",
      "unicode": "e647",
      "unicode_decimal": 58951
    },
    {
      "icon_id": "430546",
      "name": "下箭头",
      "font_class": "arrow-down",
      "unicode": "e648",
      "unicode_decimal": 58952
    },
    {
      "icon_id": "538878",
      "name": "搜索",
      "font_class": "sousuo",
      "unicode": "e61c",
      "unicode_decimal": 58908
    },
    {
      "icon_id": "566774",
      "name": "左箭头",
      "font_class": "zuojiantou",
      "unicode": "e64e",
      "unicode_decimal": 58958
    },
    {
      "icon_id": "577355",
      "name": "筛选",
      "font_class": "shaixuan",
      "unicode": "e74a",
      "unicode_decimal": 59210
    },
    {
      "icon_id": "1305463",
      "name": "查看",
      "font_class": "chakan",
      "unicode": "e63e",
      "unicode_decimal": 58942
    },
    {
      "icon_id": "1391488",
      "name": "退出登录",
      "font_class": "tuichudenglu",
      "unicode": "e649",
      "unicode_decimal": 58953
    },
    {
      "icon_id": "2076240",
      "name": " 筛选",
      "font_class": "shaixuan1",
      "unicode": "e888",
      "unicode_decimal": 59528
    },
    {
      "icon_id": "2418274",
      "name": "右箭头",
      "font_class": "youjiantou",
      "unicode": "e678",
      "unicode_decimal": 59000
    },
    {
      "icon_id": "2480667",
      "name": "首页",
      "font_class": "shouye",
      "unicode": "e630",
      "unicode_decimal": 58928
    },
    {
      "icon_id": "2815705",
      "name": "查看",
      "font_class": "chakan1",
      "unicode": "e601",
      "unicode_decimal": 58881
    },
    {
      "icon_id": "4657682",
      "name": "上传",
      "font_class": "shangchuan-",
      "unicode": "e606",
      "unicode_decimal": 58886
    },
    {
      "icon_id": "5387377",
      "name": "标签",
      "font_class": "biaoqian",
      "unicode": "eabd",
      "unicode_decimal": 60093
    },
    {
      "icon_id": "5744740",
      "name": "logout",
      "font_class": "tuichudenglu1",
      "unicode": "e605",
      "unicode_decimal": 58885
    },
    {
      "icon_id": "5838467",
      "name": "上传",
      "font_class": "shangchuan",
      "unicode": "e854",
      "unicode_decimal": 59476
    },
    {
      "icon_id": "5877283",
      "name": "夜间模式",
      "font_class": "biaoqing",
      "unicode": "e61b",
      "unicode_decimal": 58907
    },
    {
      "icon_id": "6429411",
      "name": "会议管理",
      "font_class": "huiyiguanli",
      "unicode": "e618",
      "unicode_decimal": 58904
    },
    {
      "icon_id": "7093672",
      "name": "个人中心",
      "font_class": "gerenzhongxin1",
      "unicode": "e71d",
      "unicode_decimal": 59165
    },
    {
      "icon_id": "12316642",
      "name": "个人中心",
      "font_class": "gerenzhongxin2",
      "unicode": "e61d",
      "unicode_decimal": 58909
    },
    {
      "icon_id": "12753043",
      "name": "图片",
      "font_class": "tupian_huaban",
      "unicode": "e62c",
      "unicode_decimal": 58924
    },
    {
      "icon_id": "12770686",
      "name": "已质疑",
      "font_class": "yizhiyi",
      "unicode": "e64d",
      "unicode_decimal": 58957
    },
    {
      "icon_id": "13596605",
      "name": "白天模式",
      "font_class": "baitianmoshi",
      "unicode": "e623",
      "unicode_decimal": 58915
    },
    {
      "icon_id": "14292871",
      "name": "question",
      "font_class": "question",
      "unicode": "e602",
      "unicode_decimal": 58882
    },
    {
      "icon_id": "18081869",
      "name": "夜间模式",
      "font_class": "yejianmoshi",
      "unicode": "e68b",
      "unicode_decimal": 59019
    },
    {
      "icon_id": "18310488",
      "name": "退出登录",
      "font_class": "tuichudenglu2",
      "unicode": "e61e",
      "unicode_decimal": 58910
    },
    {
      "icon_id": "20603788",
      "name": "疑问",
      "font_class": "yiwen",
      "unicode": "e69f",
      "unicode_decimal": 59039
    },
    {
      "icon_id": "21718527",
      "name": "上传会议纪要",
      "font_class": "shangchuanhuiyijiyao",
      "unicode": "e636",
      "unicode_decimal": 58934
    },
    {
      "icon_id": "23713956",
      "name": "疑问",
      "font_class": "yiwen1",
      "unicode": "e628",
      "unicode_decimal": 58920
    },
    {
      "icon_id": "27253666",
      "name": "退出登录",
      "font_class": "tuichudenglu3",
      "unicode": "e613",
      "unicode_decimal": 58899
    },
    {
      "icon_id": "28867855",
      "name": "comment-check",
      "font_class": "comment-check",
      "unicode": "ea36",
      "unicode_decimal": 59958
    },
    {
      "icon_id": "36698500",
      "name": "夜间模式",
      "font_class": "Frame-1",
      "unicode": "e64a",
      "unicode_decimal": 58954
    }
  ]
}
